Documents/verilog/Seven_Segemnt_Driver/7segdriver.v
module sev_segment_drvr ( input [3:0] hex_in,
                          output [6:0] ss_pattern_out
);
  reg a;
  reg b;
  reg c;
  reg d;
  reg e;
  reg f;
  reg g;

  always @ (hex_in) begin
    case (hex_in)
      4'h0 : begin
        a = 1'b1;
        b = 1'b1;
        c = 1'b1;
        d = 1'b1;
        e = 1'b1;
        f = 1'b1;
        g = 1'b0;
      end
      4'h1 : begin
        a = 1'b0;
        b = 1'b1;
        c = 1'b1;
        d = 1'b0;
        e = 1'b0;
        f = 1'b0;
        g = 1'b0;        
      end
      4'h2 : begin
        a = 1'b1;
        b = 1'b1;
        c = 1'b0;
        d = 1'b1;
        e = 1'b1;
        f = 1'b0;
        g = 1'b1;
      end
      4'h3 : begin
        a = 1'b1;
        b = 1'b1;
        c = 1'b1;
        d = 1'b1;
        e = 1'b0;
        f = 1'b0;
        g = 1'b1;
      end
      4'h4 : begin
        a = 1'b0;
        b = 1'b1;
        c = 1'b1;
        d = 1'b0;
        e = 1'b0;
        f = 1'b1;
        g = 1'b1;
      end
      4'h5 : begin
        a = 1'b1;
        b = 1'b0;
        c = 1'b1;
        d = 1'b1;
        e = 1'b0;
        f = 1'b1;
        g = 1'b1;
      end
      4'h6 : begin
        a = 1'b1;
        b = 1'b0;
        c = 1'b1;
        d = 1'b1;
        e = 1'b1;
        f = 1'b1;
        g = 1'b1;
      end
      4'h7 : begin
        a = 1'b1;
        b = 1'b1;
        c = 1'b1;
        d = 1'b0;
        e = 1'b0;
        f = 1'b0;
        g = 1'b0;
      end
      4'h8 : begin
        a = 1'b1;
        b = 1'b1;
        c = 1'b1;
        d = 1'b1;
        e = 1'b1;
        f = 1'b1;
        g = 1'b1;
      end
      4'h9 : begin
        a = 1'b1;
        b = 1'b1;
        c = 1'b1;
        d = 1'b0;
        e = 1'b0;
        f = 1'b1;
        g = 1'b1;
      end
      4'hA : begin
        a = 1'b1;
        b = 1'b1;
        c = 1'b1;
        d = 1'b0;
        e = 1'b1;
        f = 1'b1;
        g = 1'b1;
      end
      4'hB : begin
        a = 1'b0;
        b = 1'b0;
        c = 1'b1;
        d = 1'b1;
        e = 1'b1;
        f = 1'b1;
        g = 1'b1;
      end
      4'hC : begin
        a = 1'b1;
        b = 1'b0;
        c = 1'b0;
        d = 1'b1;
        e = 1'b1;
        f = 1'b1;
        g = 1'b0;
      end
      4'hD : begin
        a = 1'b0;
        b = 1'b1;
        c = 1'b1;
        d = 1'b1;
        e = 1'b1;
        f = 1'b0;
        g = 1'b1;
      end
      4'hE : begin
        a = 1'b1;
        b = 1'b0;
        c = 1'b0;
        d = 1'b1;
        e = 1'b1;
        f = 1'b1;
        g = 1'b1;
      end
      4'hF : begin
        a = 1'b1;
        b = 1'b0;
        c = 1'b0;
        d = 1'b0;
        e = 1'b1;
        f = 1'b1;
        g = 1'b1;
      end
      default: begin
        a = 1'b0;
        b = 1'b0;
        c = 1'b0;
        d = 1'b0;
        e = 1'b0;
        f = 1'b0;
        g = 1'b0;
      end
    endcase
  end

  assign ss_pattern_out = {a,b,c,d,e,f,g};
endmodule

Documents/verilog/Seven_Segemnt_Driver/7segdriver_tbh.v
`timescale 1ns/1ns
`include "7segdriver.v"


module sev_segment_drvr_tb;

reg [3:0] in;
reg [4:0] iteration;
wire [6:0] obs_out;

// Register containing the expected output
reg [6:0] exp_out[15:0]; 

// Instantiate the Design Under Test (DUT)
sev_segment_drvr det(in, obs_out) ;

initial begin

  $dumpfile("7segdriver_tb.vcd");
  $dumpvars(0 , sev_segment_drvr_tb);
  // Set the expected output
  exp_out[0] = 7'h7E; // 0
  exp_out[1] = 7'h30; // 1
  exp_out[2] = 7'h6D; // 2
  exp_out[3] = 7'h79; // 3
  exp_out[4] = 7'h33; // 4
  exp_out[5] = 7'h5B; // 5
  exp_out[6] = 7'h5F; // 6
  exp_out[7] = 7'h70; // 7
  exp_out[8] = 7'h7F; // 8
  exp_out[9] = 7'h73; // 9
  exp_out[10] = 7'h77; // A
  exp_out[11] = 7'h1F; // b
  exp_out[12] = 7'h4E; // C 
  exp_out[13] = 7'h3D; // d 
  exp_out[14] = 7'h4F; // E
  exp_out[15] = 7'h47; // F

  // Generate the inputs and check the output
  for (iteration = 0; iteration<=15; iteration++) begin
    
    // assign the input to the iteration variable
    in = iteration[3:0];
    
    // wait for 1 simulation tick
    #1;
 
    // Check the output
    if (obs_out != exp_out[iteration]) begin
      $display("[ERROR] Pattern [%x] Mismatch on time %0t ns Obs = %x Exp = %x",in, $time, obs_out, exp_out[iteration]);
    end
    else begin
      $display("[INFO]  Pattern [%x] Matched  on time %0t ns",in, $time);
    end
  end
  $display("Test Complete") ;
end
endmodule

Documents/verilog/Seven_Segemnt_Driver/7segdriver_tb.vcd
$date
	Tue Sep 12 10:47:34 2023
$end
$version
	Icarus Verilog
$end
$timescale
	1ns
$end
$scope module sev_segment_drvr_tb $end
$var wire 7 ! obs_out [6:0] $end
$var reg 4 " in [3:0] $end
$var reg 5 # iteration [4:0] $end
$scope module det $end
$var wire 4 $ hex_in [3:0] $end
$var wire 7 % ss_pattern_out [6:0] $end
$var reg 1 & a $end
$var reg 1 ' b $end
$var reg 1 ( c $end
$var reg 1 ) d $end
$var reg 1 * e $end
$var reg 1 + f $end
$var reg 1 , g $end
$upscope $end
$upscope $end
$enddefinitions $end
$comment Show the parameter values. $end
$dumpall
$end
#0
$dumpvars
0,
1+
1*
1)
1(
1'
1&
b1111110 %
b0 $
b0 #
b0 "
b1111110 !
$end
#1
0+
0*
0)
b110000 !
b110000 %
0&
b1 "
b1 $
b1 #
#2
1,
1*
1)
0(
b1101101 !
b1101101 %
1&
b10 "
b10 $
b10 #
#3
0*
b1111001 !
b1111001 %
1(
b11 "
b11 $
b11 #
#4
1+
0)
b110011 !
b110011 %
0&
b100 "
b100 $
b100 #
#5
1)
0'
b1011011 !
b1011011 %
1&
b101 "
b101 $
b101 #
#6
b1011111 !
b1011111 %
1*
b110 "
b110 $
b110 #
#7
0,
0+
0*
0)
b1110000 !
b1110000 %
1'
b111 "
b111 $
b111 #
#8
1,
1+
1*
b1111111 !
b1111111 %
1)
b1000 "
b1000 $
b1000 #
#9
0*
b1110011 !
b1110011 %
0)
b1001 "
b1001 $
b1001 #
#10
b1110111 !
b1110111 %
1*
b1010 "
b1010 $
b1010 #
#11
1)
0'
b11111 !
b11111 %
0&
b1011 "
b1011 $
b1011 #
#12
0,
0(
b1001110 !
b1001110 %
1&
b1100 "
b1100 $
b1100 #
#13
1,
0+
1(
1'
b111101 !
b111101 %
0&
b1101 "
b1101 $
b1101 #
#14
1+
0(
0'
b1001111 !
b1001111 %
1&
b1110 "
b1110 $
b1110 #
#15
b1000111 !
b1000111 %
0)
b1111 "
b1111 $
b1111 #
#16
b10000 #
